{
	"_id": "WishOfLuminousS1",
	"_key": "!items!WishOfLuminousS1",
	"type": "loot",
	"img": "modules/the-magic-emporium/gacha/wishes/wishOfLuminousSky.jpg",
	"name": "Wish of Luminous Sky",
	"system": {
		"description": {
			"value": "The sky opens and hides nothing. Provides perfect visibility"
		},
		"rarity": "legendary",
		"price": {
			"value": 800,
			"denomination": "gp",
			"valueInGP": 800
		}
	},
	"flags": {
		"the-magic-emporium-gacha": {
			"type": "ITEM",
			"id": "wish-of-luminous-sky",
			"operations": [
				{
					"field": "VISIBILITY_LEVEL",
					"op": "SET",
					"value": 4
				}
			]
		}
	}
}
